cli/main.py
demo/example_run_altanalyze3.py
docs/conf.py
splicespectrax/__init__.py
splicespectrax/correlation_depletion.py
splicespectrax/determine_rank.py
splicespectrax/feature_selection.py
splicespectrax/linear_svm.py
splicespectrax/main_functions.py
splicespectrax/median_impute.py
splicespectrax/metadata_analysis.py
splicespectrax/preprocess.py
splicespectrax/remove_redundancy.py
splicespectrax/round_wrapper.py
splicespectrax/run_nmf.py
splicespectrax/visualizations.py
splicespectrax-2025.0.6.dist-info/licenses/LICENSE
test/evaluations_all.py
test/max_f1_score.py
test/record_times_across_feats_full_dataset_fast_corr.py
splicespectrax-2025.0.6.dist-info/METADATA
splicespectrax-2025.0.6.dist-info/WHEEL
splicespectrax-2025.0.6.dist-info/top_level.txt
splicespectrax-2025.0.6.dist-info/RECORD
