Metadata-Version: 2.4
Name: splicespectrax
Version: 2025.0.6
Summary: Splicing-based Pattern Extraction and Clustering using TRAnscriptomics
Author-email: Kairavee Thakkar <kairavee.thakkar@cchmc.org>, Nathan Salomonis <nathan.salomonis@cchmc.org>
License-Expression: MIT
Project-URL: Repository, https://github.com/kairaveet/spectra
Project-URL: Issues, https://github.com/kairaveet/spectra/issues
Classifier: Programming Language :: Python :: 3
Classifier: Operating System :: OS Independent
Requires-Python: >=3.10
License-File: LICENSE
Requires-Dist: pandas>=2.2.2
Requires-Dist: scipy>=1.15.0
Requires-Dist: numpy==2.2.6
Requires-Dist: scikit-learn>=1.6.0
Requires-Dist: nimfa
Requires-Dist: seaborn>=0.13.0
Requires-Dist: statsmodels>=0.14.0
Requires-Dist: matplotlib>=3.10.5
Requires-Dist: scikit-dimension
Dynamic: license-file
